toast_amplicon/Amplicon_no.py
toast_amplicon/Thermo.py
toast_amplicon/__init__.py
toast_amplicon/main.py
toast_amplicon/plotting1.py
toast_amplicon/primer_selection.py
toast_amplicon/working_algo_gene_2in1.py
toast_amplicon/db/MTB-h37rv_asm19595v2-eg18.fa
toast_amplicon/db/MTB-h37rv_asm19595v2-eg18.gff
toast_amplicon/db/all_snps.csv
toast_amplicon/db/default_primer_design_setting.json
toast_amplicon/db/gene_counts.csv
toast_amplicon/db/gene_data_.csv
toast_amplicon/db/reference_design.csv
toast_amplicon/db/regions.bed
toast_amplicon/db/scratch.ipynb
toast_amplicon/db/snp_priority.csv
toast_amplicon/db/spacers.bed
toast_amplicon/db/spoligo_primer.bed
toast_amplicon/db/spoligo_primers.csv
toast_amplicon/db/tbdb.bed
toast_amplicon/db/variants copy.csv
toast_amplicon/db/variants.csv
toast_amplicon/db/variants_rpoC.csv
toast_amplicon/user_defined_files/user_input_primers.csv
toast_amplicon/user_defined_files/user_primer_design_config.json
toast_amplicon-1.5.7.dist-info/entry_points.txt
toast_amplicon-1.5.7.dist-info/licenses/LICENSE
toast_amplicon-1.5.7.dist-info/WHEEL
toast_amplicon-1.5.7.dist-info/METADATA
toast_amplicon-1.5.7.dist-info/RECORD
