Metadata-Version: 2.4
Name: toast-amplicon
Version: 1.5.7
Summary: Amplicon design tool for TB drug resistance
Author-email: Linfeng Wang <linfeng.wang@lshtm.ac.uk>
Requires-Python: <3.12
Classifier: License :: OSI Approved :: MIT License
License-File: LICENSE
Requires-Dist: pandas
Requires-Dist: numpy
Requires-Dist: plotly
Requires-Dist: rich_argparse
Requires-Dist: tabulate
Requires-Dist: primer3-py == 2.0.1
Requires-Dist: biopython
Requires-Dist: matplotlib
Project-URL: Documentation, https://github.com/linfeng-wang/TOAST
Project-URL: Source, https://github.com/linfeng-wang/TOAST
